{
  "_help": [
    "COORDENADAS DO CARNÊ - TUDO EM PONTOS (pt). Folha A4 = 595x842pt.",
    "1pt = 0.353mm. 1mm = 2.835pt.",
    "",
    "Estrutura: 2 BLOCOS por folha (carnê e via cliente, idênticos).",
    "Cada campo: x = horizontal, dy = vertical relativo ao topo do bloco.",
    "blocoY = [Y do bloco 1, Y do bloco 2].",
    "",
    "Edita pelo painel /retaguarda/carne-config + clica 'Salvar configuração'.",
    "Hot-reload: a próxima geração de PDF já usa as coords novas (sem restart)."
  ],

  "blocoY": [25, 435],
  "blocoH": 410,

  "fields": {
    "numero":        { "x": 250, "dy": 30 },
    "data":          { "x": 480, "dy": 30 },
    "cliente":       { "x": 230, "dy": 65 },
    "ultimaCompra":  { "x": 280, "dy": 95 },
    "limite":        { "x": 480, "dy": 95 },
    "pontos":        { "x": 480, "dy": 125 },
    "total":         { "x": 480, "dy": 155 },
    "entrada":       { "x": 480, "dy": 185 }
  },

  "parcelaEsq": { "xValor": 80,  "xData": 200, "dy0": 230, "dyStep": 24 },
  "parcelaDir": { "xValor": 320, "xData": 440, "dy0": 230, "dyStep": 24 },

  "totalAVencer": {
    "col1": { "x": 60,  "yStart": 700, "dyStep": 22 },
    "col2": { "x": 230, "yStart": 700, "dyStep": 22 },
    "col3": { "x": 410, "yStart": 700, "dyStep": 22 }
  }
}
